abeona/__init__.py
abeona/__main__.py
abeona/assemble.py
abeona/cli.py
abeona/reads.py
abeona/subgraphs.py
abeona/utils.py
abeona/assemble/Snakefile
abeona/assemble/__init__.py
abeona/assemble/assemble.nf
abeona/assemble/cli.py
abeona/test/__init__.py
abeona/test/drivers.py
abeona/test/expectations.py
abeona/test/utils.py
benchmark/__init__.py
benchmark/test_yeast.py
tests/__init__.py
tests/expectation/__init__.py
tests/expectation/mccortex.py
tests/test_acceptance/__init__.py
tests/test_acceptance/test_end_to_end.py
tests/test_acceptance/test_subgraphs.py
abeona-0.45.0.dist-info/LICENSE
abeona-0.45.0.dist-info/METADATA
abeona-0.45.0.dist-info/WHEEL
abeona-0.45.0.dist-info/entry_points.txt
abeona-0.45.0.dist-info/top_level.txt
abeona-0.45.0.dist-info/RECORD
