Metadata-Version: 2.1
Name: abeona
Version: 0.45.0
Summary: UNKNOWN
Home-page: https://github.com/winni2k/abeona
Author: Warren W. Kretzschmar
Author-email: warrenk@kth.se
Maintainer: Warren W. Kretzschmar
Maintainer-email: warrenk@kth.se
License: Apache-2.0
Platform: UNKNOWN
Classifier: Development Status :: 3 - Alpha
Classifier: Intended Audience :: Science/Research
Classifier: License :: OSI Approved :: Apache Software License
Classifier: Natural Language :: English
Classifier: Operating System :: OS Independent
Classifier: Programming Language :: Python :: 3.6
Classifier: Programming Language :: Python :: 3.7
Requires-Dist: cortexpy (>=0.45.6)
Requires-Dist: pandas
Requires-Dist: progressbar2
Requires-Dist: pysam
